barrel/__init__.py
barrel/core.py
barrel/install.py
barrel-0.3.0.dist-info/LICENSE
barrel-0.3.0.dist-info/WHEEL
barrel-0.3.0.dist-info/METADATA
barrel-0.3.0.dist-info/RECORD
