Metadata-Version: 2.1
Name: barrel
Version: 0.3.0
Summary: 
Home-page: https://github.com/dropseed/barrel
License: MIT
Author: Dropseed
Author-email: python@dropseed.dev
Requires-Python: >=3.6.2,<4.0.0
Classifier: License :: OSI Approved :: MIT License
Classifier: Programming Language :: Python :: 3
Classifier: Programming Language :: Python :: 3.10
Classifier: Programming Language :: Python :: 3.7
Classifier: Programming Language :: Python :: 3.8
Classifier: Programming Language :: Python :: 3.9
Project-URL: Documentation, https://github.com/dropseed/barrel
Project-URL: Repository, https://github.com/dropseed/barrel
